xarray_units/__init__.py
xarray_units/accessor.py
xarray_units/operator.py
xarray_units/py.typed
xarray_units/quantity.py
xarray_units/utils.py
xarray_units-0.5.0.dist-info/LICENSE
xarray_units-0.5.0.dist-info/METADATA
xarray_units-0.5.0.dist-info/WHEEL
xarray_units-0.5.0.dist-info/RECORD
